layrz_sdk/__init__.py
layrz_sdk/constants.py
layrz_sdk/py.typed
layrz_sdk/decorators/__init__.py
layrz_sdk/decorators/func_timing.py
layrz_sdk/entities/__init__.py
layrz_sdk/entities/action.py
layrz_sdk/entities/action_geofence_ownership.py
layrz_sdk/entities/action_kind.py
layrz_sdk/entities/action_subkind.py
layrz_sdk/entities/asset.py
layrz_sdk/entities/asset_constants.py
layrz_sdk/entities/asset_contact.py
layrz_sdk/entities/asset_operation_mode.py
layrz_sdk/entities/ats_entry.py
layrz_sdk/entities/ats_exit_history.py
layrz_sdk/entities/ats_operation.py
layrz_sdk/entities/ats_possible_entry.py
layrz_sdk/entities/ats_possible_exit.py
layrz_sdk/entities/ats_purchaseorder.py
layrz_sdk/entities/ats_reception.py
layrz_sdk/entities/case.py
layrz_sdk/entities/case_ignored_status.py
layrz_sdk/entities/case_status.py
layrz_sdk/entities/checkpoint.py
layrz_sdk/entities/command_series_ticket.py
layrz_sdk/entities/comment.py
layrz_sdk/entities/custom_field.py
layrz_sdk/entities/custom_report_page.py
layrz_sdk/entities/destination_phone.py
layrz_sdk/entities/device.py
layrz_sdk/entities/event.py
layrz_sdk/entities/exchange_service.py
layrz_sdk/entities/function.py
layrz_sdk/entities/geofence.py
layrz_sdk/entities/geofence_category.py
layrz_sdk/entities/last_message.py
layrz_sdk/entities/locator.py
layrz_sdk/entities/message.py
layrz_sdk/entities/notification_type.py
layrz_sdk/entities/operation.py
layrz_sdk/entities/operation_case_payload.py
layrz_sdk/entities/operation_payload.py
layrz_sdk/entities/operation_type.py
layrz_sdk/entities/outbound_service.py
layrz_sdk/entities/parameter_update.py
layrz_sdk/entities/platform.py
layrz_sdk/entities/position.py
layrz_sdk/entities/presence_type.py
layrz_sdk/entities/preset.py
layrz_sdk/entities/report.py
layrz_sdk/entities/report_col.py
layrz_sdk/entities/report_configuration.py
layrz_sdk/entities/report_data_type.py
layrz_sdk/entities/report_format.py
layrz_sdk/entities/report_header.py
layrz_sdk/entities/report_page.py
layrz_sdk-4.1.11.dist-info/licenses/LICENSE
layrz_sdk-4.1.11.dist-info/METADATA
layrz_sdk-4.1.11.dist-info/WHEEL
layrz_sdk-4.1.11.dist-info/top_level.txt
layrz_sdk-4.1.11.dist-info/RECORD
