Metadata-Version: 2.4
Name: layrz-sdk
Version: 4.1.11
Summary: Layrz SDK for Python
Author-email: "Golden M, Inc." <software@goldenm.com>
Maintainer-email: Kenny Mochizuki <kenny@goldenm.com>, Luis Reyes <lreyes@goldenm.com>, Kasen Li <kli@goldenm.com>, Miguel Zauzich <miguel@goldenm.com>, Angel Prieto <aprieto@goldenm.com>
License-Expression: MIT
Project-URL: Repository, https://github.com/goldenm-software/layrz-sdk
Project-URL: Changelog, https://github.com/goldenm-software/layrz-sdk/blob/main/CHANGELOG.md
Keywords: sdk,goldenm,lcl,layrz compute language,layrz
Classifier: Programming Language :: Python :: 3
Classifier: Programming Language :: Python :: 3.13
Classifier: Programming Language :: Python :: 3.14
Classifier: Operating System :: OS Independent
Classifier: Development Status :: 5 - Production/Stable
Classifier: Intended Audience :: Developers
Requires-Python: >=3.13
License-File: LICENSE
Requires-Dist: xlsxwriter<4.0.0,>=3.2.5
Requires-Dist: pydantic>=2.12.3
Requires-Dist: geopy>=2.4.1
Requires-Dist: shapely>=2.1.1
Requires-Dist: strenum>=0.4.15
Requires-Dist: requests>=2.32.4
Requires-Dist: tzdata>=2025.2
Requires-Dist: ty>=0.0.1a34
Dynamic: license-file
